smol_git/__init__.py
smol_git/__version__.py
smol_git/cli.py
smol_git/utils.py
smol_git-0.1.0.dist-info/LICENSE
smol_git-0.1.0.dist-info/METADATA
smol_git-0.1.0.dist-info/WHEEL
smol_git-0.1.0.dist-info/entry_points.txt
smol_git-0.1.0.dist-info/top_level.txt
smol_git-0.1.0.dist-info/RECORD
