Metadata-Version: 2.1
Name: smol-git
Version: 0.1.0
Summary: the smol and stupid content tracker
Home-page: https://github.com/vinayak-mehta/smol-git
Author: Vinayak Mehta
Author-email: vmehta94@gmail.com
License: Apache 2.0
Platform: UNKNOWN
Classifier: License :: OSI Approved :: Apache Software License
Classifier: Programming Language :: Python :: 3.5
Classifier: Programming Language :: Python :: 3.6
Classifier: Programming Language :: Python :: 3.7
Requires-Dist: Click (==7.0)
